mcap_owa/__init__.py
mcap_owa/decode_utils.py
mcap_owa/decoder.py
mcap_owa/hf_integration.py
mcap_owa/py.typed
mcap_owa/types.py
mcap_owa/writer.py
mcap_owa/highlevel/__init__.py
mcap_owa/highlevel/mcap_msg.py
mcap_owa/highlevel/reader.py
mcap_owa/highlevel/writer.py
mcap_owa_support-0.6.5.dist-info/METADATA
mcap_owa_support-0.6.5.dist-info/WHEEL
mcap_owa_support-0.6.5.dist-info/RECORD
