Metadata-Version: 2.4
Name: mcap-owa-support
Version: 0.6.5
Summary: OWA support for the Python MCAP library
License: MIT
Requires-Python: >=3.11
Requires-Dist: mcap>=1.0.0
Requires-Dist: orjson
Requires-Dist: owa-core==0.6.5
Requires-Dist: packaging>=20.0
Requires-Dist: pydantic>=2.0
Requires-Dist: requests>=2.32.2
